<Texts Type="Other">
	<List>
		<Text Name="NI_FSZhenWu">
			<DisplayName>Negatif - Penyaluran Relik</DisplayName>
			<Desc>Peninggalan Feng Shui di ruangan ini bertentangan dengan lingkungan sekitarnya; karakter di dalam ruangan akan terkena dampak negatif dan akibatnya kemampuannya melemah.</Desc>
		</Text>
		<Text Name="SHUN_FSZhenWu">
			<DisplayName>Positif - Penyaluran Relik</DisplayName>
			<Desc>Peninggalan Feng Shui di ruangan ini berlaku; karakter di ruangan akan terpengaruh secara positif dan sebagai hasilnya mendapatkan peningkatan kemampuan.</Desc>
		</Text>
		<Text Name="FSZhenWu_1">
			<DisplayName>Bonus Efisiensi Kerja Secara Keseluruhan</DisplayName>
		</Text>
		<Text Name="FSZhenWu_2">
			<DisplayName>Bonus Kecepatan Penyembuhan</DisplayName>
		</Text>
		<Text Name="FSZhenWu_3">
			<DisplayName>Bonus Penyembuhan</DisplayName>
		</Text>
		<Text Name="FSZhenWu_4">
			<DisplayName>Bonus Kecepatan Memasak</DisplayName>
		</Text>
		<Text Name="FSZhenWu_5">
			<DisplayName>Bonus Kecepatan Pemotongan</DisplayName>
		</Text>
		<Text Name="FSZhenWu_6">
			<DisplayName>Bonus Hasil Pemotongan Daging</DisplayName>
		</Text>
		<Text Name="FSZhenWu_7">
			<DisplayName>Bonus Kecepatan Pengerjaan Batu</DisplayName>
		</Text>
		<Text Name="FSZhenWu_8">
			<DisplayName>Bonus Kecepatan Membangun</DisplayName>
		</Text>
		<Text Name="FSZhenWu_9">
			<DisplayName>Bonus Kecepatan Bertani</DisplayName>
		</Text>
		<Text Name="FSZhenWu_10">
			<DisplayName>Bonus Kecepatan Panen</DisplayName>
		</Text>
		<Text Name="FSZhenWu_11">
			<DisplayName>Bonus Hasil Panen</DisplayName>
		</Text>
		<Text Name="FSZhenWu_12">
			<DisplayName>Bonus Kecepatan Penambangan</DisplayName>
		</Text>
		<Text Name="FSZhenWu_13">
			<DisplayName>Bonus Hasil Penambangan</DisplayName>
		</Text>
		<Text Name="FSZhenWu_14">
			<DisplayName>Bonus Peningkatan Kualitas Kerajinan</DisplayName>
		</Text>
		<Text Name="FSZhenWu_15">
			<DisplayName>Bonus Kecepatan Penempaan</DisplayName>
		</Text>
		<Text Name="FSZhenWu_16">
			<DisplayName>Bonus Kecepatan Kerajinan Tangan</DisplayName>
		</Text>
		<Text Name="FSZhenWu_17">
			<DisplayName>Bonus Kecepatan Menjahit</DisplayName>
		</Text>
		<Text Name="FSZhenWu_18">
			<DisplayName>Bonus Kecepatan Pemotongan</DisplayName>
		</Text>
		<Text Name="FSZhenWu_19">
			<DisplayName>Bonus Kecepatan Pemadam Kebakaran</DisplayName>
		</Text>
		<Text Name="FSZhenWu_20">
			<DisplayName>Bonus Kecepatan Pembersihan</DisplayName>
		</Text>
		<Text Name="FSZhenWu_21">
			<DisplayName>Bonus Nilai Suasana Hati Dasar</DisplayName>
		</Text>
		<Text Name="FSZhenWu_22">
			<DisplayName>Bonus Kecepatan Bergerak</DisplayName>
		</Text>
		<Text Name="FSZhenWu_23">
			<DisplayName>Bonus Toleransi Suhu (Dingin)</DisplayName>
		</Text>
		<Text Name="FSZhenWu_24">
			<DisplayName>Bonus Toleransi Suhu (Panas)</DisplayName>
		</Text>
		<Text Name="FSZhenWu_25">
			<DisplayName>Bonus Ketahanan Alami</DisplayName>
		</Text>
		<Text Name="FSZhenWu_26">
			<DisplayName>Bonus Toleransi Nyeri</DisplayName>
		</Text>
		<Text Name="FSZhenWu_27">
			<DisplayName>Bonus Kecepatan Belajar</DisplayName>
		</Text>
		<Text Name="FSZhenWu_28">
			<DisplayName>Bonus Peluang Terjadi Mimpi Buruk</DisplayName>
		</Text>
		<Text Name="FSZhenWu_29">
			<DisplayName>Bonus Peluang Terjadi Mimpi Manis</DisplayName>
		</Text>
		<Text Name="FSZhenWu_30">
			<DisplayName>Bonus Tingkat Konsumsi Energi</DisplayName>
		</Text>
		<Text Name="FSZhenWu_31">
			<DisplayName>Bonus Pengisian Energi</DisplayName>
		</Text>
		<Text Name="FSZhenWu_32">
			<DisplayName>Bonus Tingkat Konsumsi Makanan</DisplayName>
		</Text>
		<Text Name="FSZhenWu_33">
			<DisplayName>Bonus Tingkat Konsumsi Makanan</DisplayName>
		</Text>
		<Text Name="FSZhenWu_34">
			<DisplayName>Bonus Pengisian Makanan</DisplayName>
		</Text>
		<Text Name="FSZhenWu_35">
			<DisplayName>Bonus Tingkat Konsumsi Air</DisplayName>
		</Text>
		<Text Name="FSZhenWu_36">
			<DisplayName>Bonus Pengisian Air</DisplayName>
		</Text>
		<Text Name="FSZhenWu_37">
			<DisplayName>Bonus Tingkat Konsumsi Rekreasi</DisplayName>
		</Text>
		<Text Name="FSZhenWu_38">
			<DisplayName>Bonus Pengisian Rekreasi</DisplayName>
		</Text>
		<Text Name="FSZhenWu_39">
			<DisplayName>Bonus Kecepatan Penyempurnaan Stamina</DisplayName>
		</Text>
		<Text Name="FSZhenWu_40">
			<Desc>Bonus Pengisian Stamina</Desc>
		</Text>
		<Text Name="FSZhenWu_41">
			<DisplayName>Potensi Bonus</DisplayName>
		</Text>
		<Text Name="FSZhenWu_42">
			<DisplayName>Bonus Kecepatan Budidaya</DisplayName>
		</Text>
		<Text Name="FSZhenWu_43">
			<DisplayName>Bonus Keadaan Mental</DisplayName>
		</Text>
		<Text Name="FSZhenWu_44">
			<DisplayName>Bonus Peluang Pemahaman</DisplayName>
		</Text>
		<Text Name="FSZhenWu_45">
			<DisplayName>Bonus Kecepatan Pembuatan Artefak</DisplayName>
		</Text>
		<Text Name="FSZhenWu_46">
			<DisplayName>Bonus Tingkat Keberhasilan Pembuatan Artefak</DisplayName>
		</Text>
		<Text Name="FSZhenWu_47">
			<DisplayName>Bonus Kelas Kerajinan Artefak</DisplayName>
		</Text>
		<Text Name="FSZhenWu_48">
			<DisplayName>Bonus Kualitas Kerajinan Artefak</DisplayName>
		</Text>
		<Text Name="FSZhenWu_49">
			<DisplayName>Bonus Peluang Artefak Besar</DisplayName>
		</Text>
		<Text Name="FSZhenWu_50">
			<DisplayName>Bonus Kecepatan Alkimia</DisplayName>
		</Text>
		<Text Name="FSZhenWu_51">
			<DisplayName>Bonus Tingkat Keberhasilan Alkimia</DisplayName>
		</Text>
		<Text Name="FSZhenWu_52">
			<DisplayName>Bonus Hasil Alkimia</DisplayName>
		</Text>
		<Text Name="FSZhenWu_53">
			<DisplayName>Bonus Peluang Terobosan</DisplayName>
		</Text>
		<Text Name="FSZhenWu_54">
			<DisplayName>Bonus Pencapaian</DisplayName>
		</Text>
		<Text Name="FSZhenWu_55">
			<DisplayName>Akurasi dalam Pertempuran</DisplayName>
		</Text>
		<Text Name="FSZhenWu_56">
			<DisplayName>Menghindar dalam Pertempuran</DisplayName>
		</Text>
		<Text Name="FSZhenWu_57">
			<DisplayName>Persepsi</DisplayName>
		</Text>
		<Text Name="FSZhenWu_58">
			<DisplayName>Konstitusi</DisplayName>
		</Text>
		<Text Name="FSZhenWu_59">
			<DisplayName>Karisma</DisplayName>
		</Text>
		<Text Name="FSZhenWu_60">
			<DisplayName>Intelijen</DisplayName>
		</Text>
		<Text Name="FSZhenWu_61">
			<DisplayName>Keberuntungan</DisplayName>
		</Text>
		<Text Name="FSZhenWu_62">
			<DisplayName>Lima Atribut</DisplayName>
		</Text>
		<Text Name="SP_FSZhenWu_1a">
			<DisplayName>Segel Moralitas</DisplayName>
		</Text>
		<Text Name="SP_FSZhenWu_1b">
			<DisplayName>Segel Purba</DisplayName>
		</Text>
		<Text Name="SP_FSZhenWu_1c">
			<DisplayName>Segel Mistik</DisplayName>
		</Text>
		<Text Name="SP_FSZhenWu_2">
			<DisplayName>Pagoda Surgawi</DisplayName>
		</Text>
		<Text Name="SP_FSZhenWu_3">
			<DisplayName>Pagoda Roh</DisplayName>
		</Text>
		<Text Name="SP_FSZhenWu_4">
			<DisplayName>Kapal Yin</DisplayName>
		</Text>
		<Text Name="SP_FSZhenWu_5">
			<DisplayName>Kuali Upacara</DisplayName>
		</Text>
		<Text Name="SP_FSZhenWu_6">
			<DisplayName>Stela Roh</DisplayName>
		</Text>
		<Text Name="SP_FSZhenWu_7">
			<DisplayName>Singa Batu</DisplayName>
		</Text>
		<Text Name="SP_FSZhenWu_8">
			<DisplayName>Batu Gunung Buzhou</DisplayName>
		</Text>
		<Text Name="SP_FSZhenWu_9">
			<DisplayName>Dewan Yin Yang</DisplayName>
		</Text>
		<Text Name="SP_FSZhenWu_10">
			<DisplayName>Catatan Hidangan Abadi</DisplayName>
		</Text>
		<Text Name="SP_FSZhenWu_11">
			<DisplayName>Bagan Tanda Ilahi</DisplayName>
		</Text>
		<Text Name="SP_FSZhenWu_12">
			<DisplayName>Jimat Pesona</DisplayName>
		</Text>
		<Text Name="SP_FSZhenWu_13">
			<DisplayName>Pedang Mistik</DisplayName>
		</Text>
		<Text Name="SP_FSZhenWu_14">
			<DisplayName>Labu Tushita</DisplayName>
		</Text>
		<Text Name="SP_FSZhenWu_15">
			<DisplayName>Batang Merah Muda</DisplayName>
		</Text>
		<Text Name="SP_FSZhenWu_16">
			<DisplayName>Yang Mulia</DisplayName>
		</Text>
	</List>
</Texts>